{"includePlugins":{"template":{"count":345,"params":["badges","note","premium","data","nsfw","tabs","description","cmd","textCommand","items"]},"image":{"count":60,"params":["scale","mobileOnly","desktopOnly"]},"file":{"count":1},"markdown":{"count":50},"table":{"count":2,"params":["User","Use Case","Mantaro","mappingPath","Permission Name","Simple","Complex"]}},"fencePlugins":{"attention-note":{"count":2,"params":["label"]},"columns":{"count":101,"params":["left","right"]},"attention-warning":{"count":3,"params":["label"]},"tabs":{"count":95},"api-parameters":{"count":439,"params":["noWrap","anchorPrefix"]},"card":{"count":261,"params":["imageBackground","title","imageHeight"]}},"inlineCodePlugins":{"badge":{"count":1},"icon":{"count":174,"params":["fill","stroke"]}}}